<?xml version="1.0" encoding="UTF-8"?>
<?xml-stylesheet href="CoreNLP-to-HTML.xsl" type="text/xsl"?>
<root>
  <document>
    <sentences>
      <sentence id="1">
        <tokens>
          <token id="1">
            <word>Starbucks</word>
            <lemma>Starbucks</lemma>
            <CharacterOffsetBegin>0</CharacterOffsetBegin>
            <CharacterOffsetEnd>9</CharacterOffsetEnd>
            <POS>NNP</POS>
          </token>
          <token id="2">
            <word>Corp.</word>
            <lemma>Corp.</lemma>
            <CharacterOffsetBegin>10</CharacterOffsetBegin>
            <CharacterOffsetEnd>14</CharacterOffsetEnd>
            <POS>NNP</POS>
          </token>
          <token id="3">
            <word>.</word>
            <lemma>.</lemma>
            <CharacterOffsetBegin>14</CharacterOffsetBegin>
            <CharacterOffsetEnd>15</CharacterOffsetEnd>
            <POS>.</POS>
          </token>
        </tokens>
      </sentence>
      <sentence id="2">
        <tokens>
          <token id="1">
            <word>Enters</word>
            <lemma>enter</lemma>
            <CharacterOffsetBegin>16</CharacterOffsetBegin>
            <CharacterOffsetEnd>22</CharacterOffsetEnd>
            <POS>VBZ</POS>
          </token>
          <token id="2">
            <word>into</word>
            <lemma>into</lemma>
            <CharacterOffsetBegin>23</CharacterOffsetBegin>
            <CharacterOffsetEnd>27</CharacterOffsetEnd>
            <POS>IN</POS>
          </token>
          <token id="3">
            <word>an</word>
            <lemma>a</lemma>
            <CharacterOffsetBegin>28</CharacterOffsetBegin>
            <CharacterOffsetEnd>30</CharacterOffsetEnd>
            <POS>DT</POS>
          </token>
          <token id="4">
            <word>Agreement</word>
            <lemma>agreement</lemma>
            <CharacterOffsetBegin>31</CharacterOffsetBegin>
            <CharacterOffsetEnd>40</CharacterOffsetEnd>
            <POS>NN</POS>
          </token>
          <token id="5">
            <word>with</word>
            <lemma>with</lemma>
            <CharacterOffsetBegin>41</CharacterOffsetBegin>
            <CharacterOffsetEnd>45</CharacterOffsetEnd>
            <POS>IN</POS>
          </token>
          <token id="6">
            <word>PepsiCo</word>
            <lemma>PepsiCo</lemma>
            <CharacterOffsetBegin>46</CharacterOffsetBegin>
            <CharacterOffsetEnd>53</CharacterOffsetEnd>
            <POS>NNP</POS>
          </token>
          <token id="7">
            <word>to</word>
            <lemma>to</lemma>
            <CharacterOffsetBegin>54</CharacterOffsetBegin>
            <CharacterOffsetEnd>56</CharacterOffsetEnd>
            <POS>TO</POS>
          </token>
          <token id="8">
            <word>Sell</word>
            <lemma>sell</lemma>
            <CharacterOffsetBegin>57</CharacterOffsetBegin>
            <CharacterOffsetEnd>61</CharacterOffsetEnd>
            <POS>VB</POS>
          </token>
          <token id="9">
            <word>Starbucks</word>
            <lemma>Starbucks</lemma>
            <CharacterOffsetBegin>62</CharacterOffsetBegin>
            <CharacterOffsetEnd>71</CharacterOffsetEnd>
            <POS>NNP</POS>
          </token>
          <token id="10">
            <word>'</word>
            <lemma>'</lemma>
            <CharacterOffsetBegin>71</CharacterOffsetBegin>
            <CharacterOffsetEnd>72</CharacterOffsetEnd>
            <POS>POS</POS>
          </token>
          <token id="11">
            <word>Ready-to-drink</word>
            <lemma>ready-to-drink</lemma>
            <CharacterOffsetBegin>73</CharacterOffsetBegin>
            <CharacterOffsetEnd>87</CharacterOffsetEnd>
            <POS>JJ</POS>
          </token>
          <token id="12">
            <word>Beverages</word>
            <lemma>beverage</lemma>
            <CharacterOffsetBegin>88</CharacterOffsetBegin>
            <CharacterOffsetEnd>97</CharacterOffsetEnd>
            <POS>NNS</POS>
          </token>
          <token id="13">
            <word>in</word>
            <lemma>in</lemma>
            <CharacterOffsetBegin>98</CharacterOffsetBegin>
            <CharacterOffsetEnd>100</CharacterOffsetEnd>
            <POS>IN</POS>
          </token>
          <token id="14">
            <word>International</word>
            <lemma>International</lemma>
            <CharacterOffsetBegin>101</CharacterOffsetBegin>
            <CharacterOffsetEnd>114</CharacterOffsetEnd>
            <POS>NNP</POS>
          </token>
          <token id="15">
            <word>Markets</word>
            <lemma>Markets</lemma>
            <CharacterOffsetBegin>115</CharacterOffsetBegin>
            <CharacterOffsetEnd>122</CharacterOffsetEnd>
            <POS>NNPS</POS>
          </token>
          <token id="16">
            <word>.</word>
            <lemma>.</lemma>
            <CharacterOffsetBegin>122</CharacterOffsetBegin>
            <CharacterOffsetEnd>123</CharacterOffsetEnd>
            <POS>.</POS>
          </token>
        </tokens>
      </sentence>
      <sentence id="3">
        <tokens>
          <token id="1">
            <word>Starbucks</word>
            <lemma>Starbucks</lemma>
            <CharacterOffsetBegin>125</CharacterOffsetBegin>
            <CharacterOffsetEnd>134</CharacterOffsetEnd>
            <POS>NNP</POS>
          </token>
          <token id="2">
            <word>Corp.</word>
            <lemma>Corp.</lemma>
            <CharacterOffsetBegin>135</CharacterOffsetBegin>
            <CharacterOffsetEnd>140</CharacterOffsetEnd>
            <POS>NNP</POS>
          </token>
          <token id="3">
            <word>entered</word>
            <lemma>enter</lemma>
            <CharacterOffsetBegin>141</CharacterOffsetBegin>
            <CharacterOffsetEnd>148</CharacterOffsetEnd>
            <POS>VBD</POS>
          </token>
          <token id="4">
            <word>into</word>
            <lemma>into</lemma>
            <CharacterOffsetBegin>149</CharacterOffsetBegin>
            <CharacterOffsetEnd>153</CharacterOffsetEnd>
            <POS>IN</POS>
          </token>
          <token id="5">
            <word>an</word>
            <lemma>a</lemma>
            <CharacterOffsetBegin>154</CharacterOffsetBegin>
            <CharacterOffsetEnd>156</CharacterOffsetEnd>
            <POS>DT</POS>
          </token>
          <token id="6">
            <word>agreement</word>
            <lemma>agreement</lemma>
            <CharacterOffsetBegin>157</CharacterOffsetBegin>
            <CharacterOffsetEnd>166</CharacterOffsetEnd>
            <POS>NN</POS>
          </token>
          <token id="7">
            <word>with</word>
            <lemma>with</lemma>
            <CharacterOffsetBegin>167</CharacterOffsetBegin>
            <CharacterOffsetEnd>171</CharacterOffsetEnd>
            <POS>IN</POS>
          </token>
          <token id="8">
            <word>PepsiCo</word>
            <lemma>PepsiCo</lemma>
            <CharacterOffsetBegin>172</CharacterOffsetBegin>
            <CharacterOffsetEnd>179</CharacterOffsetEnd>
            <POS>NNP</POS>
          </token>
          <token id="9">
            <word>to</word>
            <lemma>to</lemma>
            <CharacterOffsetBegin>180</CharacterOffsetBegin>
            <CharacterOffsetEnd>182</CharacterOffsetEnd>
            <POS>TO</POS>
          </token>
          <token id="10">
            <word>sell</word>
            <lemma>sell</lemma>
            <CharacterOffsetBegin>183</CharacterOffsetBegin>
            <CharacterOffsetEnd>187</CharacterOffsetEnd>
            <POS>VB</POS>
          </token>
          <token id="11">
            <word>Starbucks</word>
            <lemma>Starbucks</lemma>
            <CharacterOffsetBegin>188</CharacterOffsetBegin>
            <CharacterOffsetEnd>197</CharacterOffsetEnd>
            <POS>NNP</POS>
          </token>
          <token id="12">
            <word>'</word>
            <lemma>'</lemma>
            <CharacterOffsetBegin>197</CharacterOffsetBegin>
            <CharacterOffsetEnd>198</CharacterOffsetEnd>
            <POS>POS</POS>
          </token>
          <token id="13">
            <word>ready-to-drink</word>
            <lemma>ready-to-drink</lemma>
            <CharacterOffsetBegin>199</CharacterOffsetBegin>
            <CharacterOffsetEnd>213</CharacterOffsetEnd>
            <POS>JJ</POS>
          </token>
          <token id="14">
            <word>beverages</word>
            <lemma>beverage</lemma>
            <CharacterOffsetBegin>214</CharacterOffsetBegin>
            <CharacterOffsetEnd>223</CharacterOffsetEnd>
            <POS>NNS</POS>
          </token>
          <token id="15">
            <word>in</word>
            <lemma>in</lemma>
            <CharacterOffsetBegin>224</CharacterOffsetBegin>
            <CharacterOffsetEnd>226</CharacterOffsetEnd>
            <POS>IN</POS>
          </token>
          <token id="16">
            <word>international</word>
            <lemma>international</lemma>
            <CharacterOffsetBegin>227</CharacterOffsetBegin>
            <CharacterOffsetEnd>240</CharacterOffsetEnd>
            <POS>JJ</POS>
          </token>
          <token id="17">
            <word>markets</word>
            <lemma>market</lemma>
            <CharacterOffsetBegin>241</CharacterOffsetBegin>
            <CharacterOffsetEnd>248</CharacterOffsetEnd>
            <POS>NNS</POS>
          </token>
          <token id="18">
            <word>,</word>
            <lemma>,</lemma>
            <CharacterOffsetBegin>248</CharacterOffsetBegin>
            <CharacterOffsetEnd>249</CharacterOffsetEnd>
            <POS>,</POS>
          </token>
          <token id="19">
            <word>including</word>
            <lemma>include</lemma>
            <CharacterOffsetBegin>250</CharacterOffsetBegin>
            <CharacterOffsetEnd>259</CharacterOffsetEnd>
            <POS>VBG</POS>
          </token>
          <token id="20">
            <word>those</word>
            <lemma>those</lemma>
            <CharacterOffsetBegin>260</CharacterOffsetBegin>
            <CharacterOffsetEnd>265</CharacterOffsetEnd>
            <POS>DT</POS>
          </token>
          <token id="21">
            <word>that</word>
            <lemma>that</lemma>
            <CharacterOffsetBegin>266</CharacterOffsetBegin>
            <CharacterOffsetEnd>270</CharacterOffsetEnd>
            <POS>WDT</POS>
          </token>
          <token id="22">
            <word>do</word>
            <lemma>do</lemma>
            <CharacterOffsetBegin>271</CharacterOffsetBegin>
            <CharacterOffsetEnd>273</CharacterOffsetEnd>
            <POS>VBP</POS>
          </token>
          <token id="23">
            <word>not</word>
            <lemma>not</lemma>
            <CharacterOffsetBegin>274</CharacterOffsetBegin>
            <CharacterOffsetEnd>277</CharacterOffsetEnd>
            <POS>RB</POS>
          </token>
          <token id="24">
            <word>have</word>
            <lemma>have</lemma>
            <CharacterOffsetBegin>278</CharacterOffsetBegin>
            <CharacterOffsetEnd>282</CharacterOffsetEnd>
            <POS>VB</POS>
          </token>
          <token id="25">
            <word>a</word>
            <lemma>a</lemma>
            <CharacterOffsetBegin>283</CharacterOffsetBegin>
            <CharacterOffsetEnd>284</CharacterOffsetEnd>
            <POS>DT</POS>
          </token>
          <token id="26">
            <word>Starbucks</word>
            <lemma>Starbucks</lemma>
            <CharacterOffsetBegin>285</CharacterOffsetBegin>
            <CharacterOffsetEnd>294</CharacterOffsetEnd>
            <POS>NNP</POS>
          </token>
          <token id="27">
            <word>presence</word>
            <lemma>presence</lemma>
            <CharacterOffsetBegin>295</CharacterOffsetBegin>
            <CharacterOffsetEnd>303</CharacterOffsetEnd>
            <POS>NN</POS>
          </token>
          <token id="28">
            <word>like</word>
            <lemma>like</lemma>
            <CharacterOffsetBegin>304</CharacterOffsetBegin>
            <CharacterOffsetEnd>308</CharacterOffsetEnd>
            <POS>IN</POS>
          </token>
          <token id="29">
            <word>India</word>
            <lemma>India</lemma>
            <CharacterOffsetBegin>309</CharacterOffsetBegin>
            <CharacterOffsetEnd>314</CharacterOffsetEnd>
            <POS>NNP</POS>
          </token>
          <token id="30">
            <word>.</word>
            <lemma>.</lemma>
            <CharacterOffsetBegin>314</CharacterOffsetBegin>
            <CharacterOffsetEnd>315</CharacterOffsetEnd>
            <POS>.</POS>
          </token>
        </tokens>
      </sentence>
      <sentence id="4">
        <tokens>
          <token id="1">
            <word>The</word>
            <lemma>the</lemma>
            <CharacterOffsetBegin>316</CharacterOffsetBegin>
            <CharacterOffsetEnd>319</CharacterOffsetEnd>
            <POS>DT</POS>
          </token>
          <token id="2">
            <word>beverages</word>
            <lemma>beverage</lemma>
            <CharacterOffsetBegin>320</CharacterOffsetBegin>
            <CharacterOffsetEnd>329</CharacterOffsetEnd>
            <POS>NNS</POS>
          </token>
          <token id="3">
            <word>would</word>
            <lemma>would</lemma>
            <CharacterOffsetBegin>330</CharacterOffsetBegin>
            <CharacterOffsetEnd>335</CharacterOffsetEnd>
            <POS>MD</POS>
          </token>
          <token id="4">
            <word>be</word>
            <lemma>be</lemma>
            <CharacterOffsetBegin>336</CharacterOffsetBegin>
            <CharacterOffsetEnd>338</CharacterOffsetEnd>
            <POS>VB</POS>
          </token>
          <token id="5">
            <word>sold</word>
            <lemma>sell</lemma>
            <CharacterOffsetBegin>339</CharacterOffsetBegin>
            <CharacterOffsetEnd>343</CharacterOffsetEnd>
            <POS>VBN</POS>
          </token>
          <token id="6">
            <word>through</word>
            <lemma>through</lemma>
            <CharacterOffsetBegin>344</CharacterOffsetBegin>
            <CharacterOffsetEnd>351</CharacterOffsetEnd>
            <POS>IN</POS>
          </token>
          <token id="7">
            <word>PepsiCo</word>
            <lemma>PepsiCo</lemma>
            <CharacterOffsetBegin>352</CharacterOffsetBegin>
            <CharacterOffsetEnd>359</CharacterOffsetEnd>
            <POS>NNP</POS>
          </token>
          <token id="8">
            <word>'s</word>
            <lemma>'s</lemma>
            <CharacterOffsetBegin>359</CharacterOffsetBegin>
            <CharacterOffsetEnd>361</CharacterOffsetEnd>
            <POS>POS</POS>
          </token>
          <token id="9">
            <word>distribution</word>
            <lemma>distribution</lemma>
            <CharacterOffsetBegin>362</CharacterOffsetBegin>
            <CharacterOffsetEnd>374</CharacterOffsetEnd>
            <POS>NN</POS>
          </token>
          <token id="10">
            <word>channels</word>
            <lemma>channel</lemma>
            <CharacterOffsetBegin>375</CharacterOffsetBegin>
            <CharacterOffsetEnd>383</CharacterOffsetEnd>
            <POS>NNS</POS>
          </token>
          <token id="11">
            <word>including</word>
            <lemma>include</lemma>
            <CharacterOffsetBegin>384</CharacterOffsetBegin>
            <CharacterOffsetEnd>393</CharacterOffsetEnd>
            <POS>VBG</POS>
          </token>
          <token id="12">
            <word>grocery</word>
            <lemma>grocery</lemma>
            <CharacterOffsetBegin>394</CharacterOffsetBegin>
            <CharacterOffsetEnd>401</CharacterOffsetEnd>
            <POS>NN</POS>
          </token>
          <token id="13">
            <word>and</word>
            <lemma>and</lemma>
            <CharacterOffsetBegin>402</CharacterOffsetBegin>
            <CharacterOffsetEnd>405</CharacterOffsetEnd>
            <POS>CC</POS>
          </token>
          <token id="14">
            <word>convenience</word>
            <lemma>convenience</lemma>
            <CharacterOffsetBegin>406</CharacterOffsetBegin>
            <CharacterOffsetEnd>417</CharacterOffsetEnd>
            <POS>NN</POS>
          </token>
          <token id="15">
            <word>stores</word>
            <lemma>store</lemma>
            <CharacterOffsetBegin>418</CharacterOffsetBegin>
            <CharacterOffsetEnd>424</CharacterOffsetEnd>
            <POS>NNS</POS>
          </token>
          <token id="16">
            <word>.</word>
            <lemma>.</lemma>
            <CharacterOffsetBegin>424</CharacterOffsetBegin>
            <CharacterOffsetEnd>425</CharacterOffsetEnd>
            <POS>.</POS>
          </token>
        </tokens>
      </sentence>
    </sentences>
  </document>
</root>
